genai_site/__init__.py
genai_site/doc_extractor/__init__.py
genai_site/doc_extractor/document_ext.py
genai_site/img_descriptor/__init__.py
genai_site/img_descriptor/image_descriptor.py
genai_site/img_generator/__init__.py
genai_site/img_generator/image_generator.py
genai_site/llm_folder/__init__.py
genai_site/llm_folder/text_generator.py
genai_site/tests/__init__.py
genai_site/tests/test_dalle.py
genai_site/tests/test_doc_ext.py
genai_site/tests/test_llm.py
genai_site_afrsv-0.1.1.dist-info/METADATA
genai_site_afrsv-0.1.1.dist-info/WHEEL
genai_site_afrsv-0.1.1.dist-info/top_level.txt
genai_site_afrsv-0.1.1.dist-info/RECORD
